linpy/__init__.py
linpy/cli.py
linpy/example.py
linpy/fetch.py
linpy/cube/__init__.py
linpy/cube/cube.py
linpy/cube/shared_dimension.py
linpy/getter/__init__.py
linpy/getter/get.py
linpy/lindas/__init__.py
linpy/lindas/namespaces.py
linpy/lindas/query.py
linpy/lindas/upload.py
lindaspy-0.4.0.dist-info/LICENSE
lindaspy-0.4.0.dist-info/METADATA
lindaspy-0.4.0.dist-info/WHEEL
lindaspy-0.4.0.dist-info/entry_points.txt
lindaspy-0.4.0.dist-info/top_level.txt
lindaspy-0.4.0.dist-info/RECORD
