Metadata-Version: 2.1
Name: lindaspy
Version: 0.4.0
Summary: Utilities for working with the linked data service LINDAS of the Swiss Federal Archives. Includes modules for working with cubes.
Author-email: Marco Kronenberg <kronenberg.marco@bafu.admin.ch>
License: MIT License
Project-URL: Homepage, https://github.com/Kronmar-Bafu/py-cube
Keywords: linked data,LINDAS,cubes,RDF
Classifier: Programming Language :: Python :: 3
Classifier: License :: OSI Approved :: MIT License
Requires-Python: >=3.12
License-File: LICENSE
Requires-Dist: numpy==2.1.3
Requires-Dist: pandas==2.2.3
Requires-Dist: pyshacl==0.26.0
Requires-Dist: pystardog==0.17.0
Requires-Dist: PyYAML==6.0.2
Requires-Dist: rdflib==7.0.0
Requires-Dist: requests==2.32.3
Requires-Dist: sparql-dataframe==0.4
Requires-Dist: SPARQLWrapper==2.0.0
